minecraft_server_updater.py
minecraft_server_updater-0.1.0.dist-info/entry_points.txt
minecraft_server_updater-0.1.0.dist-info/LICENSE
minecraft_server_updater-0.1.0.dist-info/WHEEL
minecraft_server_updater-0.1.0.dist-info/METADATA
minecraft_server_updater-0.1.0.dist-info/RECORD
